revacnlab/__init__.py
revacnlab-0.0.4.dist-info/LICENSE
revacnlab-0.0.4.dist-info/METADATA
revacnlab-0.0.4.dist-info/WHEEL
revacnlab-0.0.4.dist-info/top_level.txt
revacnlab-0.0.4.dist-info/RECORD
